{
    "backend": "flask",
    "db_name": "",
    "db_pass": "",
    "db_type": "sqlite",
    "db_user": "",
    "dbms": "1",
    "description": "generated product",
    "design": "datta-able",
    "docker": "1",
    "err_code": 0,
    "frontend": "",
    "heroku": "0",
    "pattern": "mvc",
    "pro": "0",
    "task_id": "db58ff68-989c-4548-a648-f3867f41b216",
    "task_info": "Upload Sources [0%] - 148 files",
    "task_output": "db58ff68-989c-4548-a648-f3867f41b216.zip",
    "task_result": "SUCCESS",
    "task_state": "RUNNING",
    "task_ts_end": "2023-08-29-21-43-20",
    "task_ts_start": "2023-08-29-21-43-19"
}